invoicexpress_api/__init__.py
invoicexpress_api/clients.py
invoicexpress_api/core.py
invoicexpress_api/invoices.py
invoicexpress_api-0.1.2.dist-info/METADATA
invoicexpress_api-0.1.2.dist-info/RECORD
invoicexpress_api-0.1.2.dist-info/WHEEL
invoicexpress_api-0.1.2.dist-info/top_level.txt
