Metadata-Version: 2.1
Name: invoicexpress-api
Version: 0.1.2
Summary: Thin Python 3 wrapper for the InvoiceXpress REST API
Home-page: https://github.com/bitmario/invoicexpress-api-python
Author: Mario Falcao
Author-email: mario@bitsiders.com
License: MIT license
Keywords: invoicexpress_api
Platform: UNKNOWN
Classifier: Development Status :: 2 - Pre-Alpha
Classifier: Intended Audience :: Developers
Classifier: License :: OSI Approved :: MIT License
Classifier: Natural Language :: English
Classifier: Programming Language :: Python :: 3
Classifier: Programming Language :: Python :: 3.3
Classifier: Programming Language :: Python :: 3.4
Classifier: Programming Language :: Python :: 3.5
Classifier: Programming Language :: Python :: 3.6
Requires-Dist: requests (>=2.0.1)
